dbbasic_video/__init__.py
dbbasic_video/analyze_visuals.py
dbbasic_video/cli.py
dbbasic_video/download_video.py
dbbasic_video/extract_keyframes.py
dbbasic_video/find_thumbnail.py
dbbasic_video/get_transcript.py
dbbasic_video/make_grid.py
dbbasic_video/pipeline.py
dbbasic_video/summarize.py
dbbasic_video-0.1.0.dist-info/licenses/LICENSE
dbbasic_video-0.1.0.dist-info/METADATA
dbbasic_video-0.1.0.dist-info/WHEEL
dbbasic_video-0.1.0.dist-info/entry_points.txt
dbbasic_video-0.1.0.dist-info/top_level.txt
dbbasic_video-0.1.0.dist-info/RECORD
