Metadata-Version: 2.4
Name: dbbasic-video
Version: 0.1.0
Summary: AI-powered video analysis toolkit for extracting, analyzing, and summarizing video content
Author-email: DBBasic <hello@dbbasic.com>
License: MIT
Project-URL: Homepage, https://github.com/askrobots/dbbasic-video
Project-URL: Repository, https://github.com/askrobots/dbbasic-video
Project-URL: Issues, https://github.com/askrobots/dbbasic-video/issues
Keywords: video,ai,analysis,youtube,transcript,keyframes,scene-detection
Classifier: Development Status :: 3 - Alpha
Classifier: Intended Audience :: Developers
Classifier: Topic :: Multimedia :: Video
Classifier: License :: OSI Approved :: MIT License
Classifier: Programming Language :: Python :: 3
Classifier: Programming Language :: Python :: 3.8
Classifier: Programming Language :: Python :: 3.9
Classifier: Programming Language :: Python :: 3.10
Classifier: Programming Language :: Python :: 3.11
Classifier: Programming Language :: Python :: 3.12
Requires-Python: >=3.8
License-File: LICENSE
Requires-Dist: scenedetect[opencv]>=0.6.0
Requires-Dist: opencv-python>=4.5.0
Requires-Dist: pillow>=10.0.0
Requires-Dist: youtube-transcript-api>=1.0.0
Requires-Dist: openai>=1.0.0
Requires-Dist: python-dotenv>=1.0.0
Requires-Dist: yt-dlp>=2023.0.0
Provides-Extra: dev
Requires-Dist: pytest>=7.0; extra == "dev"
Requires-Dist: black>=23.0; extra == "dev"
Requires-Dist: ruff>=0.1.0; extra == "dev"
Requires-Dist: mypy>=1.0; extra == "dev"
Dynamic: license-file
